ph_diagrams/__init__.py
ph_diagrams/ph_diagrams.py
pH_diagrams-0.3.3.dist-info/LICENSE.txt
pH_diagrams-0.3.3.dist-info/METADATA
pH_diagrams-0.3.3.dist-info/WHEEL
pH_diagrams-0.3.3.dist-info/top_level.txt
pH_diagrams-0.3.3.dist-info/RECORD
