Metadata-Version: 2.1
Name: pH-diagrams
Version: 0.3.3
Summary: Python package to plot pH diagrams
Home-page: https://github.com/chicolucio/pH-diagrams/
Author: Francisco Bustamante
Author-email: 23560423+chicolucio@users.noreply.github.com
License: MIT
Project-URL: Documentation, https://ph-diagrams.readthedocs.io/en/latest/?badge=latest
Project-URL: Source, https://github.com/chicolucio/pH-diagrams/
Project-URL: Tracker, https://github.com/chicolucio/pH-diagrams/issues
Project-URL: Download, https://pypi.org/project/pH-diagrams
Keywords: chemistry,pH,pH diagrams,distribution diagram,acid,acid-base,buffer
Platform: any
Classifier: Development Status :: 4 - Beta
Classifier: Programming Language :: Python
Classifier: Programming Language :: Python :: 3
Classifier: Operating System :: OS Independent
Classifier: License :: OSI Approved :: MIT License
Classifier: Natural Language :: English
Classifier: Intended Audience :: Science/Research
Classifier: Topic :: Scientific/Engineering
Classifier: Topic :: Scientific/Engineering :: Chemistry
Classifier: Topic :: Scientific/Engineering :: Physics
Requires-Python: >=3.8
License-File: LICENSE.txt
Requires-Dist: chempy (>0.8.0)
Requires-Dist: numpy (>1.20.0)
Requires-Dist: matplotlib (>=3.5.0)
Requires-Dist: plotly (>5.3.0)
Requires-Dist: streamlit (>1.11.0)
Requires-Dist: importlib-metadata ; python_version < "3.8"
Provides-Extra: testing
Requires-Dist: setuptools ; extra == 'testing'
Requires-Dist: pytest ; extra == 'testing'
Requires-Dist: pytest-cov ; extra == 'testing'
